airpixel/__init__.py
airpixel/__main__.py
airpixel/client.py
airpixel/dummy.py
airpixel/framework.py
airpixel/gamma_table.py
airpixel/logging_config.py
airpixel/monitor.py
airpixel/monitoring.py
airpixel/stub_device.py
airpixel-0.10.dist-info/LICENSE
airpixel-0.10.dist-info/WHEEL
airpixel-0.10.dist-info/METADATA
airpixel-0.10.dist-info/RECORD
